breaktimer/__init__.py
breaktimer/breaktimer.py
breaktimer-0.1.0.dist-info/WHEEL
breaktimer-0.1.0.dist-info/METADATA
breaktimer-0.1.0.dist-info/RECORD
