Metadata-Version: 2.1
Name: breaktimer
Version: 0.1.0
Summary: 
Author: Joben R
Author-email: joben.rara@gmail.com
Requires-Python: >=3.7,<4.0
Classifier: Programming Language :: Python :: 3
Classifier: Programming Language :: Python :: 3.7
Classifier: Programming Language :: Python :: 3.8
Requires-Dist: click (>=7.1.2,<8.0.0)
Requires-Dist: pyfiglet (>=0.8.post1,<0.9)
Requires-Dist: rich (>=6.0.0,<7.0.0)
